README.md
setup.py
tuxdrive/__init__.py
tuxdrive/tuxdrive.py
tuxdrive.egg-info/PKG-INFO
tuxdrive.egg-info/SOURCES.txt
tuxdrive.egg-info/dependency_links.txt
tuxdrive.egg-info/entry_points.txt
tuxdrive.egg-info/requires.txt
tuxdrive.egg-info/top_level.txt