Metadata-Version: 2.1
Name: tuxdrive
Version: 2.0.1
Summary: Console based DIY google drive client
Home-page: https://github.com/prahladyeri/tuxdrive
Author: Prahlad Yeri
Author-email: prahladyeri@yahoo.com
License: MIT
Platform: UNKNOWN
Classifier: Programming Language :: Python :: 3
Classifier: License :: OSI Approved :: MIT License
Classifier: Operating System :: OS Independent
Requires-Python: >= 3.4
